CHANGES.txt
LICENSE.txt
MANIFEST.in
README.rst
setup.cfg
setup.py
compressor_requirejs/__init__.py
compressor_requirejs/compiler.py
compressor_requirejs/config.py
compressor_requirejs/models.py
compressor_requirejs/tests.py
compressor_requirejs.egg-info/PKG-INFO
compressor_requirejs.egg-info/SOURCES.txt
compressor_requirejs.egg-info/dependency_links.txt
compressor_requirejs.egg-info/requires.txt
compressor_requirejs.egg-info/top_level.txt
compressor_requirejs/compressor/__init__.py
compressor_requirejs/compressor/r_precompiler.py
compressor_requirejs/resources/global_config.js
compressor_requirejs/resources/r.js
compressor_requirejs/resources/require.js