Metadata-Version: 1.1
Name: compressor-requirejs
Version: 1.3
Summary: Library for django compressor, which helps to build requirejs
Home-page: https://github.com/dresiu/compressor_requirejs
Author: Andrzej Przybyszewski
Author-email: mcendrju@gmail.com
License: GNU AGPLv3
Download-URL: https://github.com/dresiu/compressor_requirejs/tarball/1.3
Keywords: compressor_requirejs,django_compressor,django,compressor,requirejs
Platform: UNKNOWN
Classifier: Environment :: Web Environment
Classifier: Framework :: Django
Classifier: Intended Audience :: Developers
Classifier: Programming Language :: Python :: 2.7
Requires: django_compressor
Requires: PyExecJs
